rt1/__init__.py
rt1/_containers.py
rt1/_rtprocess_writer.py
rt1/general_functions.py
rt1/processing_config.py
rt1/rt1.py
rt1/rtfits.py
rt1/rtmetrics.py
rt1/rtparse.py
rt1/rtplots.py
rt1/rtprocess.py
rt1/rtresults.py
rt1/scatter.py
rt1/surface.py
rt1/volume.py
rt1-2.0.dist-info/AUTHORS
rt1-2.0.dist-info/LICENSE
rt1-2.0.dist-info/METADATA
rt1-2.0.dist-info/NOTICE
rt1-2.0.dist-info/WHEEL
rt1-2.0.dist-info/top_level.txt
rt1-2.0.dist-info/RECORD
