Metadata-Version: 2.1
Name: rt1
Version: 2.0
Summary: RT1 - bistatic single scattering radiative transfer model
Home-page: https://github.com/TUW-GEO/rt1
Author: Raphael Quast
Author-email: raphael.quast@geo.tuwien.ac.at
Maintainer: Raphael Quast
Maintainer-email: raphael.quast@geo.tuwien.ac.at
License: UNKNOWN
Keywords: physics,radiative transfer
Platform: UNKNOWN
Classifier: Intended Audience :: Science/Research
Classifier: Topic :: Scientific/Engineering :: Atmospheric Science
Classifier: Programming Language :: Python :: 3.7
Requires-Dist: numpy >=1.16
Requires-Dist: sympy >=1.4
Requires-Dist: scipy >=1.2
Requires-Dist: pandas >=0.24
Requires-Dist: matplotlib >=3.0
Provides-Extra: full
Requires-Dist: symengine >=0.4 ; extra == 'full'
Requires-Dist: xarray >=0.16 ; extra == 'full'
Requires-Dist: pytables >=3.6.1 ; extra == 'full'
